dexp/__init__.py
dexp/conftest.py
dexp/cli/__init__.py
dexp/cli/config.py
dexp/cli/defaults.py
dexp/cli/dexp_main.py
dexp/cli/install_main.py
dexp/cli/parsing.py
dexp/cli/video_main.py
dexp/cli/dexp_commands/__init__.py
dexp/cli/dexp_commands/add.py
dexp/cli/dexp_commands/background.py
dexp/cli/dexp_commands/check.py
dexp/cli/dexp_commands/copy.py
dexp/cli/dexp_commands/crop.py
dexp/cli/dexp_commands/deconv.py
dexp/cli/dexp_commands/denoise.py
dexp/cli/dexp_commands/deskew.py
dexp/cli/dexp_commands/extract_psf.py
dexp/cli/dexp_commands/fastcopy.py
dexp/cli/dexp_commands/fromraw.py
dexp/cli/dexp_commands/fuse.py
dexp/cli/dexp_commands/generic.py
dexp/cli/dexp_commands/histogram.py
dexp/cli/dexp_commands/info.py
dexp/cli/dexp_commands/projrender.py
dexp/cli/dexp_commands/register.py
dexp/cli/dexp_commands/segment.py
dexp/cli/dexp_commands/speedtest.py
dexp/cli/dexp_commands/stabilize.py
dexp/cli/dexp_commands/tiff.py
dexp/cli/dexp_commands/view.py
dexp/cli/video_commands/__init__.py
dexp/cli/video_commands/blend.py
dexp/cli/video_commands/mp4.py
dexp/cli/video_commands/overlay.py
dexp/cli/video_commands/resize.py
dexp/cli/video_commands/stack.py
dexp/cli/video_commands/volrender.py
dexp/datasets/__init__.py
dexp/datasets/base_dataset.py
dexp/datasets/clearcontrol_dataset.py
dexp/datasets/joined_dataset.py
dexp/datasets/ome_dataset.py
dexp/datasets/open_dataset.py
dexp/datasets/stack_iterator.py
dexp/datasets/tiff_dataset.py
dexp/datasets/zarr_dataset.py
dexp/datasets/demo/demo_dataset.py
dexp/datasets/operations/__init__.py
dexp/datasets/operations/background.py
dexp/datasets/operations/copy.py
dexp/datasets/operations/crop.py
dexp/datasets/operations/deconv.py
dexp/datasets/operations/denoise.py
dexp/datasets/operations/deskew.py
dexp/datasets/operations/extract_psf.py
dexp/datasets/operations/fromraw.py
dexp/datasets/operations/fuse.py
dexp/datasets/operations/generic.py
dexp/datasets/operations/histogram.py
dexp/datasets/operations/projrender.py
dexp-2023.4.10.686.dist-info/LICENSE.txt
dexp-2023.4.10.686.dist-info/METADATA
dexp-2023.4.10.686.dist-info/WHEEL
dexp-2023.4.10.686.dist-info/entry_points.txt
dexp-2023.4.10.686.dist-info/top_level.txt
dexp-2023.4.10.686.dist-info/RECORD
