Metadata-Version: 2.1
Name: dexp
Version: 2023.4.10.686
Summary: Light-sheet Dataset EXploration and Processing
Home-page: https://github.com/royerlab/dexp
Author: Jordao Bragantini, Ahmet Can Solak, Bin Yang, Loic A Royer
Author-email: jordao.bragantini@czbiohub.org, ahmetcan.solak@czbiohub.org, bin.yang@czbiohub.org, loic.royer@czbiohub.org
License: BSD 3-Clause
Classifier: License :: OSI Approved :: BSD License
Classifier: Programming Language :: Python
Classifier: Programming Language :: Python :: 3
Classifier: Programming Language :: Python :: 3.8
Classifier: Environment :: GPU :: NVIDIA CUDA :: 11.1
Classifier: Development Status :: 3 - Alpha
Classifier: Intended Audience :: Science/Research
Classifier: Topic :: Scientific/Engineering :: Image Processing
Classifier: Topic :: Scientific/Engineering :: Visualization
Requires-Python: >=3.7.0
License-File: LICENSE.txt
Requires-Dist: numpy (>=1.20)
Requires-Dist: scipy (>=1.8.0)
Requires-Dist: numcodecs
Requires-Dist: scikit-image
Requires-Dist: tifffile
Requires-Dist: tqdm
Requires-Dist: numexpr
Requires-Dist: joblib
Requires-Dist: pytest
Requires-Dist: click (>=8.0.0)
Requires-Dist: dask
Requires-Dist: dask-image
Requires-Dist: dask-cuda
Requires-Dist: distributed
Requires-Dist: zarr
Requires-Dist: cachey
Requires-Dist: gputil
Requires-Dist: gpustat
Requires-Dist: arbol
Requires-Dist: colorcet
Requires-Dist: PyYAML
Requires-Dist: cairocffi
Requires-Dist: blosc
Requires-Dist: seaborn
Requires-Dist: ome-zarr
Provides-Extra: color
Requires-Dist: colorama ; extra == 'color'
Requires-Dist: ansicolors ; extra == 'color'
Provides-Extra: cuda100
Requires-Dist: cupy-cuda100 (==10.1.0) ; extra == 'cuda100'
Provides-Extra: cuda101
Requires-Dist: cupy-cuda101 (==10.1.0) ; extra == 'cuda101'
Provides-Extra: cuda102
Requires-Dist: cupy-cuda102 (==10.1.0) ; extra == 'cuda102'
Provides-Extra: cuda110
Requires-Dist: cupy-cuda110 (==10.1.0) ; extra == 'cuda110'
Provides-Extra: cuda111
Requires-Dist: cupy-cuda111 (==10.1.0) ; extra == 'cuda111'
Provides-Extra: cuda112
Requires-Dist: cupy-cuda112 (==10.1.0) ; extra == 'cuda112'
Provides-Extra: cuda113
Requires-Dist: cupy-cuda113 (==10.1.0) ; extra == 'cuda113'
Provides-Extra: cuda114
Requires-Dist: cupy-cuda114 (==10.1.0) ; extra == 'cuda114'
Provides-Extra: dev
Requires-Dist: flake8 ; extra == 'dev'
Requires-Dist: pytest ; extra == 'dev'
Requires-Dist: coverage ; extra == 'dev'
Provides-Extra: gpu
Requires-Dist: gputools ; extra == 'gpu'
Requires-Dist: cucim ; extra == 'gpu'
Provides-Extra: napari
Requires-Dist: napari[all] ; extra == 'napari'
Provides-Extra: optional
Requires-Dist: edt ; extra == 'optional'
Requires-Dist: higra ; extra == 'optional'
Requires-Dist: pyotf ; extra == 'optional'
Requires-Dist: pyift ; extra == 'optional'
Requires-Dist: tensorstore (==0.1.16) ; extra == 'optional'
Provides-Extra: source
Requires-Dist: cupy (==10.1.0) ; extra == 'source'
